pdf2wordx1/__init__.py
pdf2wordx1/_pdf2wordx.py
pdf2wordx1/favicon.ico
pdf2wordx1/ico.ico
pdf2wordx1/files/__init__.py
pdf2wordx1/files/functions.py
pdf2wordx1/files/interfaz.py
pdf2wordx1/files/info/NOTICE
pdf2wordx1/files/info/help
pdf2wordx1-2.1.1.dist-info/licenses/LICENSE
pdf2wordx1-2.1.1.dist-info/METADATA
pdf2wordx1-2.1.1.dist-info/WHEEL
pdf2wordx1-2.1.1.dist-info/entry_points.txt
pdf2wordx1-2.1.1.dist-info/top_level.txt
pdf2wordx1-2.1.1.dist-info/RECORD
