Metadata-Version: 2.4
Name: pdf2wordx1
Version: 2.1.1
Summary: PDF to DOCX converter with UI
Author-email: Tutos Rive <tutosriveorg@gmail.com>
License: MIT License
Project-URL: Homepage, https://tutosrive.github.io/pdf2wordx/
Project-URL: Repository, https://github.com/tutosrive/pdf2wordx/
Project-URL: YouTube, https://www.youtube.com/@tutosrive
Classifier: Development Status :: 5 - Production/Stable
Classifier: Intended Audience :: End Users/Desktop
Classifier: License :: OSI Approved :: MIT License
Classifier: Programming Language :: Python :: 3
Classifier: Programming Language :: Python :: 3.8
Classifier: Programming Language :: Python :: 3.9
Classifier: Programming Language :: Python :: 3.10
Classifier: Programming Language :: Python :: 3.11
Classifier: Programming Language :: Python :: 3.12
Classifier: Operating System :: OS Independent
Classifier: Topic :: Office/Business :: Office Suites
Requires-Python: <3.13,>=3.8
License-File: LICENSE
Requires-Dist: chromologger>=0.1.4
Requires-Dist: pdf2docx>=0.5.8
Dynamic: license-file
